Metadata-Version: 2.1
Name: omip
Version: 2024.7.15
Summary: omip: utilities for processing OMIP data
Home-page: https://github.com/fzhu2e/omip
Author: Feng Zhu
Author-email: fengzhu@ucar.edu
License: MIT
Keywords: Ocean Model Intercomparison Project
Classifier: Natural Language :: English
Classifier: Programming Language :: Python :: 3.11
Classifier: Programming Language :: Python :: 3.12
License-File: LICENSE
Requires-Dist: netCDF4
Requires-Dist: xarray
Requires-Dist: dask
Requires-Dist: nc-time-axis
Requires-Dist: colorama
Requires-Dist: tqdm
